mprod/__init__.py
mprod/_base.py
mprod/_misc.py
mprod/_ml_helpers.py
mprod/_pytester.py
mprod/_pytesttester.py
mprod/decompositions/__init__.py
mprod/decompositions/_qr.py
mprod/decompositions/_tsvdm.py
mprod/decompositions/tests/__init__.py
mprod/decompositions/tests/test__qr.py
mprod/decompositions/tests/test_decompositions.py
mprod/dimensionality_reduction/__init__.py
mprod/dimensionality_reduction/_tcam.py
mprod/dimensionality_reduction/tests/__init__.py
mprod/dimensionality_reduction/tests/test_TCAM.py
mprod/tests/__init__.py
mprod/tests/_base_tests.py
mprod/tests/_utils.py
mprod/tests/test_base.py
mprod_package-0.0.3a1.dist-info/LICENSE
mprod_package-0.0.3a1.dist-info/METADATA
mprod_package-0.0.3a1.dist-info/WHEEL
mprod_package-0.0.3a1.dist-info/top_level.txt
mprod_package-0.0.3a1.dist-info/RECORD
