Metadata-Version: 2.1
Name: mprod-package
Version: 0.0.3a1
Summary: Software implementation for tensor-tensor m-product framework
Home-page: https://github.com/UriaMorP/mprod_package
Author: Uria Mor, Rafael Valdes Mas, Yotam Cohen, Haim Avron
Author-email: uriamo@gmail.com
License: BSD
Keywords: Tensor,multi way,omics,longitudinal,factorization,analysis,TCA,TCAM,PCA,M product,tensor tensor product,tSVD,tSVDM,tensor decomposition
Platform: UNKNOWN
Classifier: Development Status :: 3 - Alpha
Classifier: Intended Audience :: Science/Research
Classifier: Programming Language :: Python :: 3.6
Classifier: Programming Language :: Python :: 3.7
Classifier: Programming Language :: Python :: 3.8
Classifier: Programming Language :: Python :: 3.9
Classifier: Programming Language :: Python :: 3.10
Classifier: Programming Language :: Python :: 3 :: Only
Requires-Python: >=3.6.8
Requires-Dist: numpy (>=1.19.2)
Requires-Dist: scikit-learn (>=0.24.1)
Requires-Dist: scipy (>=1.5.3)
Requires-Dist: pandas (>=1.1.5)
Requires-Dist: dataclasses (>=0.7) ; python_version < "3.7"
Provides-Extra: dev
Requires-Dist: pytest (==6.2.2) ; extra == 'dev'
Provides-Extra: docs
Requires-Dist: sphinx-gallery (==0.9.0) ; extra == 'docs'
Requires-Dist: numpydoc (==1.1.0) ; extra == 'docs'
Requires-Dist: sphinxcontrib-bibtex (==2.3.0) ; extra == 'docs'
Requires-Dist: sphinx-prompt (==1.4.0) ; extra == 'docs'
Requires-Dist: nbsphinx (==0.8.6) ; extra == 'docs'
Requires-Dist: ipykernel (==5.4.3) ; extra == 'docs'
Requires-Dist: seaborn (==0.11.1) ; extra == 'docs'
Requires-Dist: jupyter (==1.0.0) ; extra == 'docs'
Requires-Dist: myst-parser (==0.15.2) ; extra == 'docs'
Requires-Dist: m2r2 (==0.3.1) ; extra == 'docs'
Requires-Dist: livereload (==2.6.3) ; extra == 'docs'
Requires-Dist: pandoc (==2.0.1) ; extra == 'docs'
